awsctx/__init__.py
awsctx/__main__.py
awsctx/awsctx.py
awsctx-1.0.1.dist-info/METADATA
awsctx-1.0.1.dist-info/WHEEL
awsctx-1.0.1.dist-info/entry_points.txt
awsctx-1.0.1.dist-info/top_level.txt
awsctx-1.0.1.dist-info/RECORD
