Metadata-Version: 2.1
Name: awsctx
Version: 1.0.1
Summary: A command line tool to change active AWS profiles and add/replace profiles.
Home-page: https://github.com/aurphillus/awsctx
Author: Aniket Paul
Author-email: aniketpaul446@gmail.com
License: MIT
Classifier: License :: OSI Approved :: MIT License
Classifier: Programming Language :: Python :: 2.7
Classifier: Programming Language :: Python :: 3
Classifier: Programming Language :: Python :: 3.6
Classifier: Programming Language :: Python :: 3.7
Classifier: Programming Language :: Python :: 3.8
Classifier: Programming Language :: Python :: 3.9
Requires-Python: >=3.6
